{
  "type": "insight",
  "angle": "Regional Consolidation",
  "fullPost": "**REGIONAL CONSOLIDATION**\n\nMarket reality: Smaller regional data center operators consolidating or being acquired. Market moving toward scale.\n\nHere's what this means for infrastructure operators:\n• Operators must either scale fast or specialize deeply. Middle ground disappears.\n• Speed of deployment becomes competitive advantage\n• Operators who understand this market win\n\nThe question isn't whether this happens. It's whether you're ahead of it.\n\nHow are you positioning against consolidation pressure?\n\n---\n— Tim Ryan, Pro-Tel",
  "context": "Smaller regional data center operators consolidating or being acquired. Market moving toward scale.",
  "implication": "Operators must either scale fast or specialize deeply. Middle ground disappears.",
  "source": "Northeast Market Analysis",
  "sourceUrl": "https://protelinfrastructure.com",
  "generatedAt": "2026-03-26T15:19:42.241Z",
  "status": "ready-to-post"
}